Monsoon/HVPM.py
Monsoon/LVPM.py
Monsoon/Main.py
Monsoon/Operations.py
Monsoon/__init__.py
Monsoon/calibrationData.py
Monsoon/pmapi.py
Monsoon/reflash.py
Monsoon/sampleEngine.py
Monsoon/setup.py
monsoon-0.1.88.data/data/Monsoon/Compiled/Linux/libcpp_backend.so
monsoon-0.1.88.data/data/Monsoon/Compiled/WIN32/Cpp_backend.dll
monsoon-0.1.88.dist-info/METADATA
monsoon-0.1.88.dist-info/RECORD
monsoon-0.1.88.dist-info/WHEEL
monsoon-0.1.88.dist-info/top_level.txt
